README.rst
setup.py
wlt/__init__.py
wlt.egg-info/PKG-INFO
wlt.egg-info/SOURCES.txt
wlt.egg-info/dependency_links.txt
wlt.egg-info/top_level.txt
wlt.egg-info/zip-safe