Metadata-Version: 1.1
Name: wlt
Version: 1.0.1
Summary: This is a package for wlt(USTC) loging
Home-page: https://git.ustclug.org/phys-cs-lover/wltlogin
Author: Chenxiao Liu
Author-email: Venique@mail.ustc.edu.cn
License: MIT
Keywords: python3 wlt USTC
Platform: UNKNOWN
Classifier: License :: OSI Approved :: MIT License
Classifier: Programming Language :: Python :: 3.5
Classifier: Intended Audience :: Developers
Classifier: Operating System :: OS Independent
